pyraceview/__init__.py
pyraceview/messages/__init__.py
pyraceview/messages/base.py
pyraceview/messages/car_position.py
pyraceview/messages/car_stats.py
pyraceview/messages/cup_info.py
pyraceview/messages/header.py
pyraceview/messages/heartbeat.py
pyraceview/messages/lap_info.py
pyraceview/messages/pit_lane_event.py
pyraceview/messages/pit_lane_extended.py
pyraceview/messages/pit_window.py
pyraceview/messages/race_status.py
pyraceview/messages/track_config.py
pyraceview/messages/vitc_to_lap.py
pyraceview/models/CarStats.py
pyraceview/models/Flag.py
pyraceview/models/__init__.py
pyraceview/percar/__init__.py
pyraceview/percar/lap_data.py
pyraceview/percar/pit_stop_extended_data.py
pyraceview/percar/pit_window_data.py
pyraceview/percar/points_data.py
pyraceview/percar/position_data.py
pyraceview/percar/race_status_data.py
pyraceview/percar/stats_data.py
pyraceview/util/BitBuffer.py
pyraceview/util/ByteArray.py
pyraceview/util/ByteBuffer.py
pyraceview/util/Endian.py
pyraceview/util/Vector3D.py
pyraceview/util/__init__.py
pyraceview-0.3.0.dist-info/LICENSE
pyraceview-0.3.0.dist-info/METADATA
pyraceview-0.3.0.dist-info/WHEEL
pyraceview-0.3.0.dist-info/top_level.txt
pyraceview-0.3.0.dist-info/RECORD
